setup.py
vcopt/__init__.py
vcopt/main.py
vcopt/main_154.py
vcopt/test2.py
vcopt/test_dcGA_1.py
vcopt/test_dcGA_2.py
vcopt/test_multi.py
vcopt/test_rcGA.py
vcopt/test_rcGA_1.py
vcopt/test_rcGA_2.py
vcopt/test_sample.py
vcopt/test_setGA.py
vcopt/test_tspGA.py
vcopt.egg-info/PKG-INFO
vcopt.egg-info/SOURCES.txt
vcopt.egg-info/dependency_links.txt
vcopt.egg-info/requires.txt
vcopt.egg-info/top_level.txt