Metadata-Version: 1.0
Name: vcopt
Version: 1.5.6
Summary: STOP thinking, just USE Genetic Algorithm optimizer by Viniette&Clarity.
Home-page: https://vigne-cla.com/vcopt-tutorial/
Author: Shoya Yasuda @ Viniette&Clarity, Inc.
Author-email: selamatpagi1124@gmail.com
License: Required: Copyright notice in any social outputs.     Permitted: Private Use, Commercial Use.     Forbidden: Sublicense, Modifications, Distribution, Patent Grant, Use Trademark, Hold Liable.
Platform: UNKNOWN
